spectrum_overload/__about__.py
spectrum_overload/__init__.py
spectrum_overload/differential.py
spectrum_overload/norm.py
spectrum_overload/spectrum.py
spectrum_overload/data/spec_1.fits
spectrum_overload/data/spec_wavecal.fits
spectrum_overload/data/telluric_data.ipac
spectrum_overload-0.3.dist-info/METADATA
spectrum_overload-0.3.dist-info/RECORD
spectrum_overload-0.3.dist-info/WHEEL
spectrum_overload-0.3.dist-info/entry_points.txt
spectrum_overload-0.3.dist-info/top_level.txt
