Metadata-Version: 2.1
Name: spectrum-overload
Version: 0.3
Summary: Spectrum class that overloads operators.
Home-page: https://github.com/jason-neal/spectrum_overload
Author: Jason Neal
Author-email: jason.neal@astro.up.pt
License: MIT Licence
Download-URL: https://github.com/jason-neal/spectrum_overload
Keywords: astronomy,spectra,spectroscopy,CRIRES
Platform: UNKNOWN
Classifier: Development Status :: 4 - Beta
Classifier: Intended Audience :: Science/Research
Classifier: Topic :: Scientific/Engineering :: Astronomy
Classifier: Topic :: Scientific/Engineering :: Physics
Classifier: License :: OSI Approved :: MIT License
Classifier: Programming Language :: Python :: 3
Classifier: Programming Language :: Python :: 3.5
Classifier: Programming Language :: Python :: 3.6
Classifier: Programming Language :: Python :: 3.7
Classifier: Natural Language :: English
Requires-Python: >=2.7, !=3.0.*, !=3.1.*, !=3.2.*, !=3.3.*, <4
Provides-Extra: test
Provides-Extra: docs
Provides-Extra: dev
Requires-Dist: numpy
Requires-Dist: scipy
Requires-Dist: astropy
Requires-Dist: pyastronomy
Requires-Dist: matplotlib
Provides-Extra: dev
Requires-Dist: check-manifest; extra == 'dev'
Provides-Extra: docs
Requires-Dist: sphinx (>=1.4); extra == 'docs'
Requires-Dist: sphinx-rtd-theme; extra == 'docs'
Requires-Dist: pyastronomy; extra == 'docs'
Provides-Extra: test
Requires-Dist: coverage; extra == 'test'
Requires-Dist: pytest; extra == 'test'
Requires-Dist: pytest-cov; extra == 'test'
Requires-Dist: python-coveralls; extra == 'test'
Requires-Dist: hypothesis; extra == 'test'
